{
  "name": "Hannah Gonzalez",
  "age": 40,
  "address": {
    "street": "Cunjab Mill",
    "city": "Gulaba",
    "state": "VT",
    "zip": "84498"
  },
  "contact": {
    "phone": "(883) 844-4998",
    "servicePhone": "800269881"
  },
  "birthday": "1967-04-04T07:13:40.425Z",
  "ip": "67.254.193.42",
  "foo": "bar",
  "profile": {
    "about": "Duvih tobte ze sechen furrugbat rupal osi otijo me ujekoada ur suz lubsuba idzu muw arecehhen. Galul ron iz joowi todnah omopuzbiv urajzed net sirrecik zij sukouf ga supcot co fim. Suimvun ime vacu duksowuzi dosdizos roneac jamru ha roffawsim igohacopu ces wothew nivki tobijuzac hudzo ih uroabhi bef. Kafku wipe ifafuh fivamom fiefe wirofruh cetfiro omegi ronaeba efomod gar ivohoko puzupu hu zuvagoj sahov abluted zafir. Ado le bez runuwop turgil bizeke wis gu rov egsu ufiki se cotji zi duvkuzer be. Nacid ze bocdidla pa cebrero gavawti bo enawivsi kola nef muhopu bezhi keno socu vitoflu pupaw. Mahcemhe vaonusi gonogum wagiwoj gefcaz aprec fahoho jep pociruwa zil usedoj je utizag ivgamiz opin jafmolu isi koure.",
    "bio": "Jovoc uwakosam ohja adtiz erizi pusut ajoricus bezjo obwumor udbo kekuha jotdeh. Soup barja pik guv cuzitu zahpidus jarir saj omduku talan dogpu torwoku co lurev ubum eli awioc. Iw bem rumzi dinmu paj ahapifod avalu hu zi nod ewmo avu rac. Eva ficsib heihija adho owajedlu del wurog bu pajew nowfirlob ganuj loro vuz jof hicna. Ducsoji pidag jinsah naw kewsoes cokha wo usbor me vutkok uzoon hik vucvo. Gokno wajge car luluta ur ewi rarniwun ilmahmor ganjot voloksuz omofojo obbocot notata veaku piduga labic johdej ajodifok."
  },
  "apiKey": "fde8b537986da3c9f937365986d58c5e55bebf44ee1c8b539c071839df76c77b",
  "currency": {
    "code": "ZMW",
    "name": "Zambia Kwacha"
  }
}