{
  "name": "Georgie Reid",
  "age": 32,
  "address": {
    "street": "Kawi Court",
    "city": "Waapbah",
    "state": "MA",
    "zip": "10788"
  },
  "contact": {
    "phone": "(339) 269-8225",
    "servicePhone": "800171792"
  },
  "birthday": "1990-10-01T01:07:38.667Z",
  "ip": "31.103.138.49",
  "foo": "bar",
  "profile": {
    "about": "Guhivkat daj momaf konur tom ovone sib gif acmez has hi kagbu epiewevi wa cos za doacwuf dehruf. Litirino paz pagona fumu va co fok fufac ta acahijlo wiborwev resuc zu. Nerofcob okges kapgez ma beb tibi ga esojogmu isze kulow upezognuh nokjuin jevi zak. Magew rip ra jirujnu bukuku lek re cosacgu ota im jufo kirvoen. Je tuapi ge uha mojlu pifep utruza jubdo zucpev coc gawaw toke gocazu taledro tizop da tevgem pa.",
    "bio": "Sin rihoh dinil aw ciz pate paru ertu ugkogisa mezwahteh ogibdob to okofe kis avfe ucpez ku. Su zohbab edvor rumje ilu ak kah suddet wegluk rudda hobi rako wi. Irso nos ulgol ohitade osojul fi go iwbol duwu wo fak jotu ip la vuzeza ni hoke. Wibalpok momu sofucej runpej uzaewuc mic sa uwafu havizu enoulla co ijhi. Hahzinaru ujo vedpauce esi agrislu poze wifor zojso fimuwhej kecca surza nijupco fatfu gahruiku cicbut pu zupic kikza. Viwuv hi zuna gijare dibsufpu ri jukode sovasar zaohelom gavmig nabjimar vaw dibjajde muajagu faivahu."
  },
  "apiKey": "fc6f64da389b9842a3d385bff0a0a92b2209b5f055439444751dd6836ace68bd",
  "currency": {
    "code": "NPR",
    "name": "Nepal Rupee"
  }
}